tradecalc/__init__.py
tradecalc/cli.py
tradecalc/tradecalc.py
tradecalc-0.1.2.dist-info/DESCRIPTION.rst
tradecalc-0.1.2.dist-info/METADATA
tradecalc-0.1.2.dist-info/RECORD
tradecalc-0.1.2.dist-info/WHEEL
tradecalc-0.1.2.dist-info/entry_points.txt
tradecalc-0.1.2.dist-info/metadata.json
tradecalc-0.1.2.dist-info/top_level.txt
