Metadata-Version: 2.0
Name: tradecalc
Version: 0.1.2
Summary: Collection of tools to calculate trading positions
Home-page: https://github.com/toirl/tradecalc
Author: Torsten Irländer
Author-email: torsten.irlaender@googlemail.com
License: MIT license
Keywords: tradecalc
Platform: UNKNOWN
Classifier: Development Status :: 2 - Pre-Alpha
Classifier: Intended Audience :: Developers
Classifier: License :: OSI Approved :: MIT License
Classifier: Natural Language :: English
Classifier: Programming Language :: Python :: 3.5
Classifier: Programming Language :: Python :: 3.4
Classifier: Programming Language :: Python :: 2.7
Requires-Dist: Click (>=6.0)
